ijudger/__init__.py
ijudger/judge.py
ijudger/makejson.py
ijudger-0.1.2.dist-info/METADATA
ijudger-0.1.2.dist-info/WHEEL
ijudger-0.1.2.dist-info/entry_points.txt
ijudger-0.1.2.dist-info/top_level.txt
ijudger-0.1.2.dist-info/RECORD
