Metadata-Version: 2.4
Name: ijudger
Version: 0.1.2
Summary: A small judge system for competitive programming
Home-page: https://github.com/icaijy/ijudger
Author: icaijy
Author-email: icaijy <caijunyi08@outlook.com>
License: MIT
Requires-Python: >=3.8
Dynamic: author
Dynamic: home-page
Dynamic: requires-python
